Metadata-Version: 2.1
Name: keras-layernorm-rnn
Version: 0.2.0
Summary: RNNs with layer normalization
Home-page: http://github.com/kmedian/keras-layernorm-rnn
Author: Ulf Hamster
Author-email: 554c46@gmail.com
License: MIT
Platform: UNKNOWN
Requires-Python: >=3.6
